refry/__init__.py
refry/main.py
refry-0.1.0.dist-info/METADATA
refry-0.1.0.dist-info/WHEEL
refry-0.1.0.dist-info/licenses/LICENSE
refry-0.1.0.dist-info/RECORD
