Metadata-Version: 2.3
Name: refry
Version: 0.1.0
Summary: Refry is a modern, maintained, typed easy-to-use retry decorator.
Project-URL: homepage, https://github.com/pydanny/refry
Project-URL: bugs, https://github.com/pydanny/refry/issues
Author-email: Daniel Roy Greenfeld <daniel@feldroy.com>
License-File: LICENSE
Requires-Python: >=3.8
